file_ext/__init__.py
file_ext/file_ext.py
file_ext-1.3.1.dist-info/LICENSE
file_ext-1.3.1.dist-info/METADATA
file_ext-1.3.1.dist-info/WHEEL
file_ext-1.3.1.dist-info/top_level.txt
file_ext-1.3.1.dist-info/RECORD
