Metadata-Version: 2.1
Name: file-ext
Version: 1.3.1
Summary: A Python file extension.
Home-page: https://github.com/neoctobers/py_file_ext
Author: @neoctobers
Author-email: neoctobers@gmail.com
License: UNKNOWN
Platform: UNKNOWN
Classifier: Programming Language :: Python :: 3
Classifier: License :: OSI Approved :: MIT License
Classifier: Operating System :: OS Independent
Requires-Dist: xprint
